{
  "channel_map": {
    "1": {
      "primary_channel_id": 4856923,
      "proxy_gen_channel": 4856923,
      "channel_friendly_name": "Soccer Channel 1",
      "channel_region": "us-west-2",
      "low_latency_url_source": "ws://34.212.225.202/emx/20001",
      "low_latency_url_medialive": "ws://34.212.225.202/eml/20001",
      "promos": [
        "s3://cunsco-media/vod_slates/promo1.mp4",
        "s3://cunsco-media/vod_slates/promo2.mp4",
        "s3://cunsco-media/vod_slates/promo3.mp4",
        "s3://cunsco-media/vod_slates/promo4.mp4"
      ]
    },
    "2": {
      "primary_channel_id": 1809084,
      "proxy_gen_channel": 1809084,
      "channel_friendly_name": "Soccer Channel 2",
      "channel_region": "us-west-2",
      "low_latency_url_source": "ws://34.212.225.202/emx/20002",
      "low_latency_url_medialive": "ws://34.212.225.202/eml/20002",
      "promos": [
        "s3://cunsco-media/vod_slates/promo1.mp4",
        "s3://cunsco-media/vod_slates/promo2.mp4",
        "s3://cunsco-media/vod_slates/promo3.mp4",
        "s3://cunsco-media/vod_slates/promo4.mp4"
      ]
    }
  },
  "vod_bucket":"schedule-action-assets",
  "channel_start_slate":"",
  "promo_bucket_region": "us-west-2",
  "control_api_endpoint_url": "https://69s54i4koc.execute-api.us-west-2.amazonaws.com/v1/dashboard-ctrl",
  "control_api_endpoint_host_header":"",
  "dashboard_title":"My Streaming Dashboard"
}